LICENSE
MANIFEST.in
README
setup.cfg
setup.py
Flask_OpenID.egg-info/PKG-INFO
Flask_OpenID.egg-info/SOURCES.txt
Flask_OpenID.egg-info/dependency_links.txt
Flask_OpenID.egg-info/namespace_packages.txt
Flask_OpenID.egg-info/not-zip-safe
Flask_OpenID.egg-info/requires.txt
Flask_OpenID.egg-info/top_level.txt
docs/.DS_Store
docs/Makefile
docs/conf.py
docs/index.rst
docs/make.bat
docs/_static/.DS_Store
docs/_static/flask-openid.png
docs/_themes/flask_theme_support.py
docs/_themes/flask/theme.conf
docs/_themes/flask/static/flasky.css_t
docs/_themes/flask_small/layout.html
docs/_themes/flask_small/theme.conf
docs/_themes/flask_small/static/flasky.css_t
example/example.py
example/static/openid.png
example/static/style.css
example/templates/create_profile.html
example/templates/edit_profile.html
example/templates/index.html
example/templates/layout.html
example/templates/login.html
flaskext/__init__.py
flaskext/openid.py