Metadata-Version: 1.0
Name: Flask-OpenID
Version: 1.0.1
Summary: OpenID support for Flask
Home-page: http://github.com/mitsuhiko/flask-openid/
Author: Armin Ronacher
Author-email: armin.ronacher@active-4.com
License: BSD
Platform: any
Classifier: Development Status :: 4 - Beta
Classifier: Environment :: Web Environment
Classifier: Intended Audience :: Developers
Classifier: License :: OSI Approved :: BSD License
Classifier: Operating System :: OS Independent
Classifier: Programming Language :: Python
Classifier: Topic :: Internet :: WWW/HTTP :: Dynamic Content
Classifier: Topic :: Software Development :: Libraries :: Python Modules
